{"id":"node_modules/graphql/jsutils/isPromise.mjs","dependencies":[{"name":"/Users/asketes/jsc/node_modules/graphql/package.json","includedInParent":true,"mtime":1521233986000},{"name":"/Users/asketes/jsc/package.json","includedInParent":true,"mtime":1532879252421}],"generated":{"js":"'use strict';\n\nObject.defineProperty(exports, \"__esModule\", {\n   value: true\n});\nexports.default = isPromise;\n\n\n// eslint-disable-next-line no-redeclare\nfunction isPromise(value) {\n   return Boolean(value && typeof value.then === 'function');\n} /**\n   * Copyright (c) 2015-present, Facebook, Inc.\n   *\n   * This source code is licensed under the MIT license found in the\n   * LICENSE file in the root directory of this source tree.\n   *\n   *  strict\n   */\n\n/**\n * Returns true if the value acts like a Promise, i.e. has a \"then\" function,\n * otherwise returns false.\n */","map":{"mappings":[{"name":"isPromise","generated":{"line":6,"column":18},"source":"node_modules/graphql/jsutils/isPromise.mjs","original":{"line":4,"column":24}},{"generated":{"line":9,"column":0},"source":"node_modules/graphql/jsutils/isPromise.mjs","original":{"line":3,"column":0}},{"generated":{"line":10,"column":0},"source":"node_modules/graphql/jsutils/isPromise.mjs","original":{"line":4,"column":15}},{"name":"isPromise","generated":{"line":10,"column":9},"source":"node_modules/graphql/jsutils/isPromise.mjs","original":{"line":4,"column":24}},{"generated":{"line":10,"column":18},"source":"node_modules/graphql/jsutils/isPromise.mjs","original":{"line":4,"column":15}},{"name":"value","generated":{"line":10,"column":19},"source":"node_modules/graphql/jsutils/isPromise.mjs","original":{"line":4,"column":34}},{"generated":{"line":10,"column":24},"source":"node_modules/graphql/jsutils/isPromise.mjs","original":{"line":4,"column":15}},{"generated":{"line":10,"column":26},"source":"node_modules/graphql/jsutils/isPromise.mjs","original":{"line":4,"column":41}},{"generated":{"line":11,"column":0},"source":"node_modules/graphql/jsutils/isPromise.mjs","original":{"line":5,"column":2}},{"name":"Boolean","generated":{"line":11,"column":10},"source":"node_modules/graphql/jsutils/isPromise.mjs","original":{"line":5,"column":9}},{"name":"value","generated":{"line":11,"column":18},"source":"node_modules/graphql/jsutils/isPromise.mjs","original":{"line":5,"column":17}},{"generated":{"line":11,"column":27},"source":"node_modules/graphql/jsutils/isPromise.mjs","original":{"line":5,"column":26}},{"name":"value","generated":{"line":11,"column":34},"source":"node_modules/graphql/jsutils/isPromise.mjs","original":{"line":5,"column":33}},{"name":"then","generated":{"line":11,"column":40},"source":"node_modules/graphql/jsutils/isPromise.mjs","original":{"line":5,"column":39}},{"generated":{"line":11,"column":44},"source":"node_modules/graphql/jsutils/isPromise.mjs","original":{"line":5,"column":26}},{"generated":{"line":11,"column":49},"source":"node_modules/graphql/jsutils/isPromise.mjs","original":{"line":5,"column":48}},{"generated":{"line":11,"column":59},"source":"node_modules/graphql/jsutils/isPromise.mjs","original":{"line":5,"column":9}},{"generated":{"line":11,"column":60},"source":"node_modules/graphql/jsutils/isPromise.mjs","original":{"line":5,"column":2}},{"generated":{"line":12,"column":0},"source":"node_modules/graphql/jsutils/isPromise.mjs","original":{"line":6,"column":1}},{"generated":{"line":12,"column":2},"source":"node_modules/graphql/jsutils/isPromise.mjs","original":{"line":6,"column":2}},{"generated":{"line":21,"column":0},"source":"node_modules/graphql/jsutils/isPromise.mjs","original":{"line":15,"column":0}}],"sources":{"node_modules/graphql/jsutils/isPromise.mjs":"\n\n// eslint-disable-next-line no-redeclare\nexport default function isPromise(value) {\n  return Boolean(value && typeof value.then === 'function');\n} /**\n   * Copyright (c) 2015-present, Facebook, Inc.\n   *\n   * This source code is licensed under the MIT license found in the\n   * LICENSE file in the root directory of this source tree.\n   *\n   *  strict\n   */\n\n/**\n * Returns true if the value acts like a Promise, i.e. has a \"then\" function,\n * otherwise returns false.\n */"},"lineCount":null}},"hash":"0adde0d4045004621e5a1f3402084d06","cacheData":{"env":{}}}